{
  "name": "Atravesar lo Sólido",
  "type": "spell",
  "img": "icons/svg/item-bag.svg",
  "effects": [],
  "folder": "q3oC02n7VitMjxGx",
  "flags": {
    "core": {},
    "cf": {
      "id": "temp_wdbq4hjo6mc",
      "color": "#000000"
    }
  },
  "system": {
    "level": {
      "value": 32
    },
    "via": {
      "value": "earth"
    },
    "spellType": {
      "value": "effect"
    },
    "actionType": {
      "value": "active"
    },
    "combatType": {
      "value": "none"
    },
    "hasDailyMaintenance": {
      "value": false
    },
    "critic": {
      "value": "-"
    },
    "visible": false,
    "macro": "",
    "grades": {
      "base": {
        "name": {
          "value": ""
        },
        "intRequired": {
          "value": 7
        },
        "zeon": {
          "value": 80
        },
        "maintenanceCost": {
          "value": "5"
        },
        "description": {
          "value": "Presencia máxima 100."
        }
      },
      "intermediate": {
        "name": {
          "value": ""
        },
        "intRequired": {
          "value": 10
        },
        "zeon": {
          "value": 100
        },
        "maintenanceCost": {
          "value": "5"
        },
        "description": {
          "value": "Presencia máxima 140."
        }
      },
      "advanced": {
        "name": {
          "value": ""
        },
        "intRequired": {
          "value": 12
        },
        "zeon": {
          "value": 120
        },
        "maintenanceCost": {
          "value": "10"
        },
        "description": {
          "value": "Presencia máxima 180."
        }
      },
      "arcane": {
        "name": {
          "value": ""
        },
        "intRequired": {
          "value": 14
        },
        "zeon": {
          "value": 140
        },
        "maintenanceCost": {
          "value": "10"
        },
        "description": {
          "value": "Presencia máxima 240."
        }
      }
    }
  },
  "_stats": {
    "systemId": "animabf",
    "systemVersion": "1.18.0-beta2",
    "coreVersion": "11.315",
    "createdTime": 1690991082135,
    "modifiedTime": 1709815603681,
    "lastModifiedBy": "s1iIg3oHOkECBfdY"
  },
  "_id": "HpoiiZNPCCfygkE9",
  "sort": 0,
  "ownership": {
    "default": 0,
    "jsmBo00pwrK7EnHs": 3
  },
  "_key": "!items!HpoiiZNPCCfygkE9"
}
